<?xml version="1.0" encoding="UTF-8"?>
<text id="1270_paris-notredame_228799" id_text_code="paris-notredame" num_cema="228799" tokens="-" unknows="-" nams="-" source="SdVNP" num_base="-" corpus="Paris (Notre-Dame)" date="1270" date_cema14="-" date_ed="4-2-1270" authenticite="-" etat="-" original="-" tradition="-" langue_lem="-" langue="-" support="-" chirographe="-" sceau="-" analyse="Symon de Decani Villa, Petrus dictus Bos et Stephanus Palmerii, de Roseto in Bria, clerici, asserunt homines laicos Roseti, aratrum habentes, corveiam unam canonicis Parisiensibus, ejusdem loci prebendariis, annuatim debere, seque, quanquam clericos, eidem corveiæ, si jubeat capitulum, subjiciunt." edition="GUÉRARD Benjamin (éd.), Cartulaire de l'église Notre-Dame de Paris, tome 2, Paris, Imprimerie impériale, 1850, Pars 3, Liber 09, n° 028." pays="France" region="Île-de-France" diocese="-" auteur_code="-" beneficiaire_code="-" auteur_nom="-" beneficiaire_nom="-" auteur_lieu="-" action="-" genre="-">
<s>
<w pos="SENT" lemma=".">.</w>
</s>
<s>
<w pos="VBE" lemma="do">Datum</w>
<w pos="SUB" lemma="annus">anno</w>
<w pos="SUB" lemma="dominus">Domini</w>
<w pos="NUM" lemma="1000">m</w>
<w pos="NUM" lemma="200">cc</w>
<w pos="NUM" lemma="sexagesimus">sexagesimo</w>
<w pos="NUM" lemma="nonus">nono</w>
<w pos="PON" lemma=",">,</w>
<w pos="SUB" lemma="dies">die</w>
<w pos="NAM" lemma="-">martis</w>
<w pos="PRE" lemma="post2">post</w>
<w pos="SUB" lemma="festa1">festum</w>
<w pos="SUB" lemma="purificatio">purificationis</w>
<w pos="QLF" lemma="beatus">beate</w>
<w pos="NAM" lemma="--">Marie</w>
<w pos="SUB" lemma="uirgo">uirginis</w>
<w pos="SENT" lemma=".">.</w>
</s>
</text>
