<?xml version="1.0" encoding="UTF-8"?>
<text id="1308_paris-notredame_229430" id_text_code="paris-notredame" num_cema="229430" tokens="-" unknows="-" nams="-" source="SdVNP" num_base="-" corpus="Paris (Notre-Dame)" date="1308" date_cema14="-" date_ed="12-1-1308" authenticite="-" etat="-" original="-" tradition="-" langue_lem="-" langue="-" support="-" chirographe="-" sceau="-" analyse="Littera dimidii arpenti terre traditi ad censum Guillelmo dicto Foulon de Villa Cereris." edition="GUÉRARD Benjamin (éd.), Cartulaire de l'église Notre-Dame de Paris, tome 3, Paris, Imprimerie impériale, 1850, Pars 4, Liber 01, n° 166." pays="France" region="Île-de-France" diocese="-" auteur_code="-" beneficiaire_code="-" auteur_nom="-" beneficiaire_nom="-" auteur_lieu="-" action="-" genre="-">
<s>
<w pos="QLF" lemma="uniuersus">Uniuersis</w>
<w pos="PON" lemma=",">,</w>
<w pos="VBE" lemma="--">etc.</w>
<w pos="NAM" lemma="-">Guillermus</w>
<w pos="VBE" lemma="dico2">dictus</w>
<w pos="NAM" lemma="--">Foulon</w>
<w pos="PRE" lemma="de">de</w>
<w pos="NAM" lemma="--">Uilla</w>
<w pos="NAM" lemma="--">Cereris</w>
<w pos="VBE" lemma="assero1">asseruit</w>
<w pos="CON" lemma="et">et</w>
<w pos="VBE" lemma="confiteor">confessus</w>
<w pos="VBE" lemma="sum">est</w>
<w pos="PON" lemma=",">,</w>
<w pos="PRE" lemma="coram2">coram</w>
<w pos="PRO" lemma="nos">nobis</w>
<w pos="PON" lemma=",">,</w>
<w pos="PRO" lemma="se">se</w>
<w pos="VBE" lemma="accipio">accepisse</w>
<w pos="ADV" lemma="imperpetuum">imperpetuum</w>
<w pos="PON" lemma=",">,</w>
<w pos="PRE" lemma="pro">pro</w>
<w pos="PRO" lemma="se">se</w>
<w pos="CON" lemma="et">et</w>
<w pos="QLF" lemma="suus">suis</w>
<w pos="SUB" lemma="heres">heredibus</w>
<w pos="CON" lemma="atque">ac</w>
<w pos="SUB" lemma="causa2">causam</w>
<w pos="VBE" lemma="habeo">habituris</w>
<w pos="PRE" lemma="a">ab</w>
<w pos="PRO" lemma="idem2">eodem</w>
<w pos="PON" lemma=",">,</w>
<w pos="PRE" lemma="a">a</w>
<w pos="SUB" lemma="dominus">domino</w>
<w pos="NAM" lemma="--">Guillermo</w>
<w pos="PON" lemma=",">,</w>
<w pos="SUB" lemma="receptor">receptore</w>
<w pos="SUB" lemma="dominus">domini</w>
<w pos="NAM" lemma="--">Parisiensis</w>
<w pos="SUB" lemma="episcopus">episcopi</w>
<w pos="PON" lemma=",">,</w>
<w pos="SUB" lemma="dimidium">dimidium</w>
<w pos="SUB" lemma="aripennis">arpentum</w>
<w pos="SUB" lemma="terra">terre</w>
<w pos="QLF" lemma="arabilis">arabilis</w>
<w pos="PON" lemma=",">,</w>
<w pos="VBE" lemma="sino">situm</w>
<w pos="PRE" lemma="in">in</w>
<w pos="SUB" lemma="territorium">territorio</w>
<w pos="NAM" lemma="--">Uille</w>
<w pos="NAM" lemma="--">Cereris</w>
<w pos="PON" lemma=",">,</w>
<w pos="PRE" lemma="in">in</w>
<w pos="SUB" lemma="locus">loco</w>
<w pos="PRO" lemma="qui2">qui</w>
<w pos="VBE" lemma="dico2">dicitur</w>
<w pos="VBE" lemma="--">la</w>
<w pos="NAM" lemma="--">Grosse</w>
<w pos="NAM" lemma="--">Pierre</w>
<w pos="SENT" lemma=".">.</w>
</s>
<s>
<w pos="PON" lemma=",">,</w>
<w pos="PRE" lemma="pro">pro</w>
<w pos="NUM" lemma="unus">una</w>
<w pos="SUB" lemma="mina">mina</w>
<w pos="SUB" lemma="auena">auene</w>
<w pos="CON" lemma="et">et</w>
<w pos="SUB" lemma="dimidium">dimidio</w>
<w pos="NAM" lemma="--">minoto</w>
<w pos="SUB" lemma="frumentum">frumenti</w>
<w pos="PON" lemma=",">,</w>
<w pos="VBE" lemma="reddo">reddendis</w>
<w pos="CON" lemma="et">et</w>
<w pos="VBE" lemma="soluo">soluendis</w>
<w pos="SUB" lemma="annus">anno</w>
<w pos="QLF" lemma="quilibet1">quolibet</w>
<w pos="PRE" lemma="in">in</w>
<w pos="QLF" lemma="posterus">posterum</w>
<w pos="VBE" lemma="dico2">dicto</w>
<w pos="SUB" lemma="dominus">domino</w>
<w pos="NAM" lemma="--">Parisiensi</w>
<w pos="SUB" lemma="episcopus">episcopo</w>
<w pos="CON" lemma="et">et</w>
<w pos="PRO" lemma="is2">eius</w>
<w pos="SUB" lemma="successor">successoribus</w>
<w pos="PON" lemma=",">,</w>
<w pos="PRE" lemma="in">in</w>
<w pos="SUB" lemma="granarium">graneriis</w>
<w pos="NAM" lemma="--">Parisiensibus</w>
<w pos="PON" lemma=",">,</w>
<w pos="PRE" lemma="a">ab</w>
<w pos="PRO" lemma="idem2">eodem</w>
<w pos="NAM" lemma="--">Guillermo</w>
<w pos="VBE" lemma="dico2">dicto</w>
<w pos="NAM" lemma="--">Felon</w>
<w pos="CON" lemma="et">et</w>
<w pos="PRO" lemma="is2">eius</w>
<w pos="SUB" lemma="heres">heredibus</w>
<w pos="CON" lemma="siue">seu</w>
<w pos="SUB" lemma="causa2">causam</w>
<w pos="PRE" lemma="a">ab</w>
<w pos="PRO" lemma="ipse2">ipso</w>
<w pos="VBE" lemma="habeo">habituris</w>
<w pos="PON" lemma=",">,</w>
<w pos="ADV" lemma="una">una</w>
<w pos="PRE" lemma="cum1">cum</w>
<w pos="QLF" lemma="alius">aliis</w>
<w pos="SUB" lemma="redditus2">redditibus</w>
<w pos="PRE" lemma="in">in</w>
<w pos="ADV" lemma="antea">antea</w>
<w pos="VBE" lemma="dico2">dicto</w>
<w pos="SUB" lemma="dominus">domino</w>
<w pos="NAM" lemma="--">Parisiensi</w>
<w pos="SUB" lemma="episcopus">episcopo</w>
<w pos="PRE" lemma="super">super</w>
<w pos="QLF" lemma="dictus">dicto</w>
<w pos="SUB" lemma="dimidium">dimidio</w>
<w pos="SUB" lemma="aripennis">arpento</w>
<w pos="SUB" lemma="terra">terre</w>
<w pos="VBE" lemma="debeo">debitis</w>
<w pos="SENT" lemma=".">.</w>
</s>
<s>
<w pos="VBE" lemma="do">Datum</w>
<w pos="SUB" lemma="annus">anno</w>
<w pos="SUB" lemma="dominus">Domini</w>
<w pos="NUM" lemma="millesimus">millesimo</w>
<w pos="NUM" lemma="trecentesimus">trecentesimo</w>
<w pos="NUM" lemma="septimus1">septimo</w>
<w pos="PON" lemma=",">,</w>
<w pos="SUB" lemma="dies">die</w>
<w pos="SUB" lemma="sabbatum">sabbati</w>
<w pos="PRE" lemma="post2">post</w>
<w pos="SUB" lemma="epiphania1">epiphaniam</w>
<w pos="PRO" lemma="idem2">eiusdem</w>
<w pos="SENT" lemma=".">.</w>
</s>
</text>
